enum_patch.py
enum_patch-0.3.dist-info/METADATA
enum_patch-0.3.dist-info/WHEEL
enum_patch-0.3.dist-info/top_level.txt
enum_patch-0.3.dist-info/RECORD
